pliffy/__init__.py
pliffy/demo.py
pliffy/estimate.py
pliffy/parser.py
pliffy/plot.py
pliffy/utils.py
pliffy/figure/__init__.py
pliffy/figure/diff_axis.py
pliffy/figure/figure.py
pliffy/figure/figure_ab.py
pliffy/figure/figure_diff.py
tests/__init__.py
tests/conftest.py
tests/test_demo.py
tests/test_diff_axis_creator.py
tests/test_estimate.py
tests/test_figure_ab.py
tests/test_figure_diff.py
tests/test_parser.py
tests/test_utils.py
pliffy-0.1.3.dist-info/LICENSE
pliffy-0.1.3.dist-info/METADATA
pliffy-0.1.3.dist-info/WHEEL
pliffy-0.1.3.dist-info/top_level.txt
pliffy-0.1.3.dist-info/RECORD
