Metadata-Version: 2.1
Name: pliffy
Version: 0.1.3
Summary: Plotting differences with Python
Home-page: https://github.com/MartinHeroux/pliffy
Author: Martin Héroux
Author-email: heroux.martin@gmail.com
License: GNU General Public License v3 or later (GPLv3+)
Platform: UNKNOWN
Classifier: License :: OSI Approved :: GNU General Public License v3 (GPLv3)
Classifier: Programming Language :: Python :: 3.8
Requires-Dist: matplotlib (>=3.3.1)
Requires-Dist: numpy (>=1.19.1)
Requires-Dist: scipy (>=1.5.2)
